guietta/__init__.py
guietta/__version__.py
guietta/guietta.py
guietta/guietta_matplotlib.py
guietta/guietta_pyqtgraph.py
guietta/examples/__init__.py
guietta/examples/all.py
guietta/examples/base.py
guietta/examples/button_renamed.py
guietta/examples/buttons.py
guietta/examples/calculator.py
guietta/examples/checkbox.py
guietta/examples/compact.py
guietta/examples/continuations.py
guietta/examples/derive.py
guietta/examples/derive_unbound.py
guietta/examples/duplicate.py
guietta/examples/events.py
guietta/examples/events_custom.py
guietta/examples/events_custom_get.py
guietta/examples/filedialog.py
guietta/examples/font.py
guietta/examples/get.py
guietta/examples/get_nonblock.py
guietta/examples/get_timeout.py
guietta/examples/groupbox.py
guietta/examples/images.py
guietta/examples/images_compact.py
guietta/examples/imshow.py
guietta/examples/line_edit.py
guietta/examples/listbox.py
guietta/examples/messagebox.py
guietta/examples/password.py
guietta/examples/plot.py
guietta/examples/plot_animated.py
guietta/examples/plot_projection.py
guietta/examples/plot_property.py
guietta/examples/plot_pyqtgraph.py
guietta/examples/progress_bar.py
guietta/examples/progress_bar_title.py
guietta/examples/properties.py
guietta/examples/radio.py
guietta/examples/rename.py
guietta/examples/signal_property.py
guietta/examples/slider.py
guietta/examples/slider_get.py
guietta/examples/stretch.py
guietta/examples/sub_layout.py
guietta/examples/sum.py
guietta/examples/sum_auto.py
guietta/examples/sum_button_with.py
guietta/examples/sum_combobox.py
guietta/examples/sum_combobox_with.py
guietta/examples/sum_events.py
guietta/examples/sum_properties.py
guietta/examples/sum_with.py
guietta/examples/sum_with_function.py
guietta/examples/timer.py
guietta/examples/valueslider.py
guietta/examples/with_import.py
guietta-1.6.3.dist-info/LICENSE
guietta-1.6.3.dist-info/METADATA
guietta-1.6.3.dist-info/WHEEL
guietta-1.6.3.dist-info/top_level.txt
guietta-1.6.3.dist-info/RECORD
