Metadata-Version: 2.1
Name: guietta
Version: 1.6.3
Summary: Simple GUI for Python
Home-page: https://github.com/alfiopuglisi/guietta
Author: Alfio Puglisi
Author-email: alfio.puglisi@inaf.it
License: MIT
Classifier: Development Status :: 4 - Beta
Classifier: Operating System :: POSIX :: Linux
Classifier: Programming Language :: Python :: 3
License-File: LICENSE
Requires-Dist: PySide2
